gcvit_tensorflow/__init__.py
gcvit_tensorflow/version.json
gcvit_tensorflow/models/__init__.py
gcvit_tensorflow/models/config.py
gcvit_tensorflow/models/gcvit.py
gcvit_tensorflow/models/utils.py
gcvit_tensorflow/models/layers/__init__.py
gcvit_tensorflow/models/layers/feat_extract.py
gcvit_tensorflow/models/layers/gcvit_block.py
gcvit_tensorflow/models/layers/gcvit_layer.py
gcvit_tensorflow/models/layers/global_query_gen.py
gcvit_tensorflow/models/layers/mlp.py
gcvit_tensorflow/models/layers/patch_embed.py
gcvit_tensorflow/models/layers/reduce_size.py
gcvit_tensorflow/models/layers/se.py
gcvit_tensorflow/models/layers/utils.py
gcvit_tensorflow/models/layers/window_attention.py
gcvit_tensorflow/models/layers/window_attention_global.py
gcvit_tensorflow-1.2.1.dist-info/LICENSE
gcvit_tensorflow-1.2.1.dist-info/METADATA
gcvit_tensorflow-1.2.1.dist-info/WHEEL
gcvit_tensorflow-1.2.1.dist-info/top_level.txt
gcvit_tensorflow-1.2.1.dist-info/RECORD
